dstoolbox/__init__.py
snakebox/__init__.py
snakeutils-0.0.1.dist-info/LICENSE
snakeutils-0.0.1.dist-info/METADATA
snakeutils-0.0.1.dist-info/WHEEL
snakeutils-0.0.1.dist-info/top_level.txt
snakeutils-0.0.1.dist-info/RECORD
