Metadata-Version: 2.1
Name: snakeutils
Version: 0.0.1
Summary: A collection of tools used by the Datasnakes.
Home-page: https://github.com/snakeutils
Author: Datasnakes
Author-email: datasnakes@gmail.com
License: MIT
